MANIFEST.in
README.md
requirements.txt
setup.cfg
setup.py
ToE/__init__.py
ToE.egg-info/PKG-INFO
ToE.egg-info/SOURCES.txt
ToE.egg-info/dependency_links.txt
ToE.egg-info/requires.txt
ToE.egg-info/top_level.txt
ToE/communication/GradBlock.py
ToE/communication/Gradcomp.py
ToE/communication/MPIManager.py
ToE/communication/__init__.py
ToE/communication/socketutils.py
ToE/subgraph/__init__.py
ToE/subgraph/dynamic_split_model.py