Metadata-Version: 1.1
Name: ToE
Version: 0.0.1a0
Summary: An edge-cloud collaborative training system for CNN and other DNNs.
Home-page: https://github.com/yhqjohn/ToE
Author: 余翰乔, 董元睿
Author-email: yhqjohn@gmail.com
License: BSD
Download-URL: https://github.com/yhqjohn/ToE/tarball/0.0.1-alpha
Platform: UNKNOWN
Classifier: Development Status :: 3 - Alpha
Classifier: Intended Audience :: Developers
Classifier: Programming Language :: Python :: 3
